signinid/__init__.py
signinid/_async_client.py
signinid/_client.py
signinid/errors.py
signinid/types.py
signinid/resources/__init__.py
signinid/resources/_base.py
signinid/resources/inbox.py
signinid/resources/sent.py
signinid-0.1.0.dist-info/METADATA
signinid-0.1.0.dist-info/WHEEL
signinid-0.1.0.dist-info/licenses/LICENSE
signinid-0.1.0.dist-info/RECORD
