Metadata-Version: 2.4
Name: signinid
Version: 0.1.0
Summary: Python SDK for SigninID sandbox email testing API
Project-URL: Homepage, https://app.signinid.com
Project-URL: Documentation, https://app.signinid.com/docs
Project-URL: Repository, https://github.com/peerborough/signinid-python-sdk
Project-URL: Issues, https://github.com/peerborough/signinid-python-sdk/issues
Author-email: Peerborough <contact@peerborough.com>
License-Expression: MIT
License-File: LICENSE
Keywords: automation,e2e,email,login,otp,sandbox,signinid,signup,smtp,testing,verification
Classifier: Development Status :: 4 - Beta
Classifier: Intended Audience :: Developers
Classifier: License :: OSI Approved :: MIT License
Classifier: Programming Language :: Python :: 3
Classifier: Programming Language :: Python :: 3.10
Classifier: Programming Language :: Python :: 3.11
Classifier: Programming Language :: Python :: 3.12
Classifier: Programming Language :: Python :: 3.13
Classifier: Typing :: Typed
Requires-Python: >=3.10
Requires-Dist: httpx>=0.27.0
Provides-Extra: dev
Requires-Dist: mypy>=1.8.0; extra == 'dev'
Requires-Dist: pytest-asyncio>=0.23.0; extra == 'dev'
Requires-Dist: pytest-httpx>=0.30.0; extra == 'dev'
Requires-Dist: pytest>=8.0.0; extra == 'dev'
Requires-Dist: ruff>=0.3.0; extra == 'dev'
